pyhfp/__init__.py
pyhfp/hfp.cpython-310-darwin.so
pyhfp/utils.py
tests/__init__.py
tests/test_pyhfp.py
pyhfp-0.1.dist-info/LICENSE
pyhfp-0.1.dist-info/METADATA
pyhfp-0.1.dist-info/WHEEL
pyhfp-0.1.dist-info/top_level.txt
pyhfp-0.1.dist-info/RECORD
