Metadata-Version: 2.1
Name: pyhfp
Version: 0.1
Summary: Hierarchical Fitting Primitives.
Home-page: https://github.com/philippmoehl/py-hfp
Author: Philipp Moehl
Author-email: philipp1994@gmail.com
Requires-Python: >=3.7
License-File: LICENSE
Requires-Dist: numpy (==1.26.0)
Requires-Dist: trimesh (==3.23.5)
Provides-Extra: test
Requires-Dist: pytest ; extra == 'test'
